examples
seth
