Metadata-Version: 1.1
Name: seth
Version: 0.3.6
Summary: Smart and practical set of utilities for Pyramid framework
Home-page: https://github.com/jnosal/seth
Author: jnosal
Author-email: jacek.nosal@outlook.com
License: UNKNOWN
Keywords: sqlalchemy,pyramid
Platform: UNKNOWN
Classifier: Development Status :: 1 - Planning
Classifier: Intended Audience :: Developers
Classifier: Framework :: Pyramid
Classifier: Natural Language :: English
Classifier: License :: OSI Approved :: MIT License
Classifier: Operating System :: OS Independent
Classifier: Programming Language :: Python
Classifier: Programming Language :: Python :: 2
Classifier: Programming Language :: Python :: 2.6
Classifier: Programming Language :: Python :: 2.7
Classifier: Topic :: Software Development :: Libraries :: Python Modules
